click_reviewers_tools-0.84.data/scripts/click-check-bin-path
click_reviewers_tools-0.84.data/scripts/click-check-content-hub
click_reviewers_tools-0.84.data/scripts/click-check-desktop
click_reviewers_tools-0.84.data/scripts/click-check-framework
click_reviewers_tools-0.84.data/scripts/click-check-functional
click_reviewers_tools-0.84.data/scripts/click-check-lint
click_reviewers_tools-0.84.data/scripts/click-check-online-accounts
click_reviewers_tools-0.84.data/scripts/click-check-push-helper
click_reviewers_tools-0.84.data/scripts/click-check-scope
click_reviewers_tools-0.84.data/scripts/click-check-security
click_reviewers_tools-0.84.data/scripts/click-check-systemd
click_reviewers_tools-0.84.data/scripts/click-check-url-dispatcher
click_reviewers_tools-0.84.data/scripts/click-review
click_reviewers_tools-0.84.data/scripts/click-run-checks
click_reviewers_tools-0.84.data/scripts/click-show-files
clickreviews/__init__.py
clickreviews/apparmor.py
clickreviews/common.py
clickreviews/cr_bin_path.py
clickreviews/cr_common.py
clickreviews/cr_content_hub.py
clickreviews/cr_desktop.py
clickreviews/cr_framework.py
clickreviews/cr_functional.py
clickreviews/cr_language_packs.py
clickreviews/cr_lint.py
clickreviews/cr_online_accounts.py
clickreviews/cr_push_helper.py
clickreviews/cr_scope.py
clickreviews/cr_security.py
clickreviews/cr_skeleton.py
clickreviews/cr_systemd.py
clickreviews/cr_tests.py
clickreviews/cr_url_dispatcher.py
clickreviews/frameworks.py
clickreviews/modules.py
clickreviews/overrides.py
clickreviews/remote.py
clickreviews/tests/__init__.py
clickreviews/tests/test_aaa_example_cr_skeleton.py
clickreviews/tests/test_cr_bin_path.py
clickreviews/tests/test_cr_common.py
clickreviews/tests/test_cr_content_hub.py
clickreviews/tests/test_cr_desktop.py
clickreviews/tests/test_cr_framework.py
clickreviews/tests/test_cr_lint.py
clickreviews/tests/test_cr_online_accounts.py
clickreviews/tests/test_cr_push_helper.py
clickreviews/tests/test_cr_scope.py
click_reviewers_tools-0.84.dist-info/COPYING
click_reviewers_tools-0.84.dist-info/METADATA
click_reviewers_tools-0.84.dist-info/WHEEL
click_reviewers_tools-0.84.dist-info/top_level.txt
click_reviewers_tools-0.84.dist-info/RECORD
