Metadata-Version: 2.1
Name: click-reviewers-tools
Version: 0.84
License-File: COPYING
Requires-Dist: python-magic
Requires-Dist: PyYaml
Requires-Dist: lxml
Requires-Dist: pyxdg
Requires-Dist: python-apt
Requires-Dist: python-debian
